yedi/__init__.py
yedi/container.py
yedi-0.2.0.dist-info/LICENSE
yedi-0.2.0.dist-info/METADATA
yedi-0.2.0.dist-info/WHEEL
yedi-0.2.0.dist-info/RECORD
