Metadata-Version: 2.3
Name: yedi
Version: 0.2.0
Summary: Lightweight dependency injection library for Python
License: MIT
Keywords: dependency-injection,di,ioc,inversion-of-control,container
Author: Elena Loonstra
Requires-Python: >=3.10
Classifier: Development Status :: 4 - Beta
Classifier: Intended Audience :: Developers
Classifier: License :: OSI Approved :: MIT License
Classifier: Programming Language :: Python :: 3
Classifier: Programming Language :: Python :: 3.10
Classifier: Programming Language :: Python :: 3.11
Classifier: Programming Language :: Python :: 3.12
Classifier: Programming Language :: Python :: 3.13
Classifier: Topic :: Software Development :: Libraries :: Python Modules
Classifier: Typing :: Typed
Project-URL: Homepage, https://github.com/eloonstra/yedi
Project-URL: Issues, https://github.com/eloonstra/yedi/issues
Project-URL: Repository, https://github.com/eloonstra/yedi
